<?xml version = '1.0' encoding = 'UTF-8'?>
<Relation class="oracle.dbtools.crest.model.design.logical.Relation" name="Relation_8" directorySegmentName="seg_0" id="C8777DA9-6A3A-BCE1-9C67-D6E3206782EF">
<createdBy>gerar</createdBy>
<createdTime>2022-03-04 23:46:58 UTC</createdTime>
<ownerDesignName>Proyecto1</ownerDesignName>
<engineerTo>
<item key="2AB79113-A7F4-B6A1-BF22-AC5D46DA074B" value="true"/>
</engineerTo>
<sourcePk>F0682938-177F-6367-5654-22CC14E03E39</sourcePk>
<identifying>false</identifying>
<optionalSource>true</optionalSource>
<optionalTarget>false</optionalTarget>
<sourceCardinality>1</sourceCardinality>
<sourceEntity>B373EDE3-F912-E755-1130-F93853A52414</sourceEntity>
<targetCardinalityString>*</targetCardinalityString>
<targetEntity>920A83A5-685A-1B37-03D9-0CE39CB4B1B8</targetEntity>
<transferable>true</transferable>
<deleteRule>NO ACTION</deleteRule>
</Relation>